Metadata-Version: 1.1
Name: vncorenlp
Version: 1.0.3
Summary: A Python wrapper for VnCoreNLP using a bidirectional communication channel.
Home-page: https://github.com/dnanhkhoa/python-vncorenlp
Author: Khoa Duong
Author-email: dnanhkhoa@live.com
License: MIT
Keywords: python-vncorenlp vncorenlp nlp vietnamese-nlp parser word-segmentation tokenizer pos-tagger named-entity-recognition ner dependency-parser
Platform: UNKNOWN
Classifier: Development Status :: 5 - Production/Stable
Classifier: Intended Audience :: Developers
Classifier: Intended Audience :: Science/Research
Classifier: License :: OSI Approved :: MIT License
Classifier: Programming Language :: Python :: 3
Classifier: Topic :: Text Processing :: Linguistic
